indianatau/__init__.py
indianatau-0.6.4.dist-info/WHEEL
indianatau-0.6.4.dist-info/METADATA
indianatau-0.6.4.dist-info/RECORD
